gpu_stress/__init__.py
gpu_stress/__main__.py
gpu_stress/core.py
gpu_stress-1.0.0.dist-info/METADATA
gpu_stress-1.0.0.dist-info/WHEEL
gpu_stress-1.0.0.dist-info/entry_points.txt
gpu_stress-1.0.0.dist-info/licenses/LICENSE
gpu_stress-1.0.0.dist-info/RECORD
