Metadata-Version: 2.4
Name: gpu-stress
Version: 1.0.0
Summary: Command-line utility for stressing GPUs using PyTorch.
Author-email: Geoffrey Lentner <glentner@purdue.edu>, Jacob Verburgt <verburgt@purdue.edu>
License-Expression: MIT
License-File: LICENSE
Keywords: command-line,utility
Classifier: Development Status :: 5 - Production/Stable
Classifier: License :: OSI Approved :: MIT License
Classifier: Programming Language :: Python :: 3.12
Classifier: Programming Language :: Python :: 3.13
Classifier: Programming Language :: Python :: 3.14
Requires-Python: >=3.12
Requires-Dist: cmdkit>=2.7.7
Requires-Dist: numpy>=2.2.6
Requires-Dist: torch>=2.7.1
